companycam/__init__.py
companycam/api.py
companycam/client.py
companycam/exceptions.py
companycam/manager.py
companycam/models.py
companycam/py.typed
companycam/types.py
companycam/utils.py
companycam/v2/__init__.py
companycam/v2/defaults.py
companycam/v2/managers.py
companycam/v2/models.py
companycam_unofficial-0.2.3.dist-info/LICENSE
companycam_unofficial-0.2.3.dist-info/METADATA
companycam_unofficial-0.2.3.dist-info/WHEEL
companycam_unofficial-0.2.3.dist-info/top_level.txt
companycam_unofficial-0.2.3.dist-info/RECORD
