Metadata-Version: 2.1
Name: companycam-unofficial
Version: 0.2.3
Summary: Python client and bindings for CompanyCam API.
Author-email: elyas <elyas@ely.as>
License: MIT
Project-URL: Issue Tracker, https://github.com/ely-as/python-companycam/issues
Project-URL: Source, https://github.com/ely-as/python-companycam
Keywords: python,companycam
Classifier: Development Status :: 4 - Beta
Classifier: Intended Audience :: Developers
Classifier: License :: OSI Approved :: MIT License
Classifier: Programming Language :: Python :: 3
Classifier: Programming Language :: Python :: 3 :: Only
Classifier: Programming Language :: Python :: 3.10
Classifier: Programming Language :: Python :: 3.11
Classifier: Programming Language :: Python :: 3.12
Classifier: Typing :: Typed
Requires-Python: >=3.10
License-File: LICENSE
Requires-Dist: httpx <1
Requires-Dist: pydantic <3
Provides-Extra: test
Requires-Dist: black ; extra == 'test'
Requires-Dist: jsonschema ; extra == 'test'
Requires-Dist: mypy ; extra == 'test'
Requires-Dist: pytest ; extra == 'test'
Requires-Dist: pytest-cov >=4.1 ; extra == 'test'
Requires-Dist: pytest-mock ; extra == 'test'
Requires-Dist: pyyaml ; extra == 'test'
Requires-Dist: ruff ; extra == 'test'
Requires-Dist: types-jsonschema ; extra == 'test'
Requires-Dist: types-PyYAML ; extra == 'test'
Requires-Dist: types-mock ; extra == 'test'
Requires-Dist: types-setuptools ; extra == 'test'
